unstable/__init__.py
unstable/_types.py
unstable/actor.py
unstable/buffers.py
unstable/collector.py
unstable/game_scheduler.py
unstable/model_registry.py
unstable/runtime.py
unstable/terminal_interface.py
unstable/trackers.py
unstable/learners/__init__.py
unstable/learners/a2c_learner.py
unstable/learners/base.py
unstable/learners/reinforce_learner.py
unstable/learners/utils.py
unstable/reward_transformations/__init__.py
unstable/reward_transformations/transformation_final.py
unstable/reward_transformations/transformation_sampling.py
unstable/reward_transformations/transformation_step.py
unstable/samplers/__init__.py
unstable/samplers/env_samplers.py
unstable/samplers/model_samplers.py
unstable/utils/__init__.py
unstable/utils/logging.py
unstable/utils/misc.py
unstable/utils/templates.py
unstable_rl-0.2.1.dist-info/licenses/LICENSE
unstable_rl-0.2.1.dist-info/METADATA
unstable_rl-0.2.1.dist-info/WHEEL
unstable_rl-0.2.1.dist-info/entry_points.txt
unstable_rl-0.2.1.dist-info/top_level.txt
unstable_rl-0.2.1.dist-info/RECORD
