Metadata-Version: 2.4
Name: unstable-rl
Version: 0.2.1
Summary: An Async Online Multi-Agent RL library for training reasoning models on TextArena games.
Author-email: Leon Guertler <Guertlerlo@cfar.a-star.edu.sg>
License: MIT License
Project-URL: Homepage, https://github.com/LeonGuertler/UnstableBaselines
Requires-Python: >=3.10
License-File: LICENSE
Requires-Dist: textarena
Requires-Dist: wandb
Requires-Dist: vllm
Requires-Dist: ray>=2.43.0
Requires-Dist: torch
Requires-Dist: transformers
Requires-Dist: peft
Requires-Dist: trueskill
Requires-Dist: pynvml
Requires-Dist: dm-tree
Dynamic: license-file
